[
  {
    "id": "lhmp_table_837206baae01455a",
    "city": "alameda",
    "source_document": "alameda-cahmp-2022.pdf",
    "pdf_page": 3,
    "page_label": "",
    "section_heading": "",
    "suggested_hazard": null,
    "extraction_reason": "PDF text matched a figure or table caption pattern.",
    "review_status": "candidate",
    "caption": "Table of Contents | i",
    "extracted_text": "Table of Contents | i Table of Contents Executive Summary ................................................................................................................................... v Climate and Natural Hazard Risks in Alameda ........................................................................................ vii Focus on Equity ....................................................................................................................................... viii Climate Adaptation and Hazard Mitigation Strategy ................................................................................ ix Vision............................................................................................................................................... ix Hazard Mitigation and Adaptation Goals ........................................................................................ ix Hazard Specific Goals ..................................................................................................................... ix Completed Strategies ....................................................................................................................... x Priority Climate Adaptation and Hazard Mitigation Strategies ........................................................ xi Implementation and Updates .................................................................................................................. xiv Background ............................................................................................................................................ 1-2 Purpose .................................................................................................................................................. 1-2 Key Terms .............................................................................................................................................. 1-3 Relationship to Other Plans .................................................................................................................... 1-3",
    "page_image_path": "data/lhmp/extracted/alameda/page-images/page-0003.png"
  },
  {
    "id": "lhmp_table_f313e4ac508fd7f3",
    "city": "alameda",
    "source_document": "alameda-cahmp-2022.pdf",
    "pdf_page": 3,
    "page_label": "",
    "section_heading": "",
    "suggested_hazard": null,
    "extraction_reason": "PDF text matched a figure or table caption pattern.",
    "review_status": "candidate",
    "caption": "Table of Contents",
    "extracted_text": "Table of Contents Executive Summary ................................................................................................................................... v Climate and Natural Hazard Risks in Alameda ........................................................................................ vii Focus on Equity ....................................................................................................................................... viii Climate Adaptation and Hazard Mitigation Strategy ................................................................................ ix Vision............................................................................................................................................... ix Hazard Mitigation and Adaptation Goals ........................................................................................ ix Hazard Specific Goals ..................................................................................................................... ix Completed Strategies ....................................................................................................................... x Priority Climate Adaptation and Hazard Mitigation Strategies ........................................................ xi Implementation and Updates .................................................................................................................. xiv Background ............................................................................................................................................ 1-2 Purpose .................................................................................................................................................. 1-2 Key Terms .............................................................................................................................................. 1-3 Relationship to Other Plans .................................................................................................................... 1-3 Focus on Equity ...................................................................................................................................... 1-4",
    "page_image_path": "data/lhmp/extracted/alameda/page-images/page-0003.png"
  },
  {
    "id": "lhmp_table_da66fb5e482d0d88",
    "city": "alameda",
    "source_document": "alameda-cahmp-2022.pdf",
    "pdf_page": 4,
    "page_label": "",
    "section_heading": "",
    "suggested_hazard": "earthquake",
    "extraction_reason": "Caption contained configured hazard alias “earthquake”.",
    "review_status": "candidate",
    "caption": "Table of Contents | ii",
    "extracted_text": "Table of Contents | ii Table of Contents (Continued) Race and Ethnicity ........................................................................................................................ 3-3 Household Composition ................................................................................................................ 3-3 Income and Employment .............................................................................................................. 3-3 Social Vulnerability Assessment (CARP) ...................................................................................... 3-5 Alameda Economy ................................................................................................................................. 3-6 Employment .................................................................................................................................. 3-6 Buildings ................................................................................................................................................. 3-7 Residential Buildings ..................................................................................................................... 3-7 City Owned Buildings .................................................................................................................... 3-8 Buildings Owned by Other Agencies ............................................................................................ 3-8 Care Facilities ............................................................................................................................... 3-9 Land Use ................................................................................................................................................ 3-9 Utilities .................................................................................................................................................. 3-10 Stormwater and Sewer Systems ................................................................................................. 3-12",
    "page_image_path": "data/lhmp/extracted/alameda/page-images/page-0004.png"
  },
  {
    "id": "lhmp_table_7996abc40f13530b",
    "city": "alameda",
    "source_document": "alameda-cahmp-2022.pdf",
    "pdf_page": 4,
    "page_label": "",
    "section_heading": "",
    "suggested_hazard": "earthquake",
    "extraction_reason": "Caption contained configured hazard alias “earthquake”.",
    "review_status": "candidate",
    "caption": "Table of Contents (Continued)",
    "extracted_text": "Table of Contents (Continued) Race and Ethnicity ........................................................................................................................ 3-3 Household Composition ................................................................................................................ 3-3 Income and Employment .............................................................................................................. 3-3 Social Vulnerability Assessment (CARP) ...................................................................................... 3-5 Alameda Economy ................................................................................................................................. 3-6 Employment .................................................................................................................................. 3-6 Buildings ................................................................................................................................................. 3-7 Residential Buildings ..................................................................................................................... 3-7 City Owned Buildings .................................................................................................................... 3-8 Buildings Owned by Other Agencies ............................................................................................ 3-8 Care Facilities ............................................................................................................................... 3-9 Land Use ................................................................................................................................................ 3-9 Utilities .................................................................................................................................................. 3-10 Stormwater and Sewer Systems ................................................................................................. 3-12 Drinking Water System ............................................................................................................... 3-13",
    "page_image_path": "data/lhmp/extracted/alameda/page-images/page-0004.png"
  },
  {
    "id": "lhmp_table_d56cb47cf655b096",
    "city": "alameda",
    "source_document": "alameda-cahmp-2022.pdf",
    "pdf_page": 5,
    "page_label": "",
    "section_heading": "",
    "suggested_hazard": "flood",
    "extraction_reason": "Caption contained configured hazard alias “flooding”.",
    "review_status": "candidate",
    "caption": "Table of Contents | iii",
    "extracted_text": "Table of Contents | iii Table of Contents (Continued) Future Tsunamis ......................................................................................................................... 4-31 Tsunami Risk Assessment .......................................................................................................... 4-34 Evacuation Planning ................................................................................................................... 4-34 Heat ...................................................................................................................................................... 4-36 Drought ................................................................................................................................................. 4-39 Wildfire-Related Hazards...................................................................................................................... 4-42 Smoky Air .................................................................................................................................... 4-43 Public Safety Power Shut-offs (PSPS) ....................................................................................... 4-46 Dam Breach Inundation ........................................................................................................................ 4-47 Other Hazards Not Considered in this Plan ......................................................................................... 4-49 Climate Adaptation and Hazard Mitigation Strategy Development ........................................................ 5-2 Capabilities Assessment ........................................................................................................................ 5-2 Planning and Regulatory ............................................................................................................... 5-2 Administrative and Technical ........................................................................................................ 5-3",
    "page_image_path": "data/lhmp/extracted/alameda/page-images/page-0005.png"
  },
  {
    "id": "lhmp_table_e4ce5cdef69a75dd",
    "city": "alameda",
    "source_document": "alameda-cahmp-2022.pdf",
    "pdf_page": 5,
    "page_label": "",
    "section_heading": "",
    "suggested_hazard": "flood",
    "extraction_reason": "Caption contained configured hazard alias “flooding”.",
    "review_status": "candidate",
    "caption": "Table of Contents (Continued)",
    "extracted_text": "Table of Contents (Continued) Future Tsunamis ......................................................................................................................... 4-31 Tsunami Risk Assessment .......................................................................................................... 4-34 Evacuation Planning ................................................................................................................... 4-34 Heat ...................................................................................................................................................... 4-36 Drought ................................................................................................................................................. 4-39 Wildfire-Related Hazards...................................................................................................................... 4-42 Smoky Air .................................................................................................................................... 4-43 Public Safety Power Shut-offs (PSPS) ....................................................................................... 4-46 Dam Breach Inundation ........................................................................................................................ 4-47 Other Hazards Not Considered in this Plan ......................................................................................... 4-49 Climate Adaptation and Hazard Mitigation Strategy Development ........................................................ 5-2 Capabilities Assessment ........................................................................................................................ 5-2 Planning and Regulatory ............................................................................................................... 5-2 Administrative and Technical ........................................................................................................ 5-3 Fiscal ............................................................................................................................................. 5-4",
    "page_image_path": "data/lhmp/extracted/alameda/page-images/page-0005.png"
  },
  {
    "id": "lhmp_table_f9c3383ba28285d8",
    "city": "alameda",
    "source_document": "alameda-cahmp-2022.pdf",
    "pdf_page": 6,
    "page_label": "",
    "section_heading": "",
    "suggested_hazard": "sea_level_rise",
    "extraction_reason": "Caption contained configured hazard alias “sea level rise”.",
    "review_status": "candidate",
    "caption": "Table of Contents | iv",
    "extracted_text": "Table of Contents | iv List of Appendices APPENDIX A— Planning Process APPENDIX B— Public Outreach APPENDIX C— Community Survey APPENDIX D— Detailed Asset Inventory APPENDIX E— Detailed Earthquake Risk Assessment APPENDIX F— Detailed Flooding and Sea Level Rise Risk Assessment APPENDIX G— Priority Coastal Inundation Locations APPENDIX H— Additional Maps APPENDIX I— Approval Documentation",
    "page_image_path": "data/lhmp/extracted/alameda/page-images/page-0006.png"
  },
  {
    "id": "lhmp_table_f2fe33ea202a12f6",
    "city": "alameda",
    "source_document": "alameda-cahmp-2022.pdf",
    "pdf_page": 37,
    "page_label": "",
    "section_heading": "Age Characteristics",
    "suggested_hazard": "sea_level_rise",
    "extraction_reason": "Caption contained configured hazard alias “coastal flooding”.",
    "review_status": "candidate",
    "caption": "Table 3-1 Population Age Distribution, 2000–2019",
    "extracted_text": "Table 3-1 Population Age Distribution, 2000–2019 Age Group Alameda Population 2000 2010 2019 Under 15 18.0% 17.1% 17.4% 15 – 19 5.5% 5.7% 4.9% 20 – 34 20.4%",
    "page_image_path": ""
  },
  {
    "id": "lhmp_table_14d7e1bc04e3c636",
    "city": "alameda",
    "source_document": "alameda-cahmp-2022.pdf",
    "pdf_page": 38,
    "page_label": "",
    "section_heading": "",
    "suggested_hazard": null,
    "extraction_reason": "PDF text matched a figure or table caption pattern.",
    "review_status": "candidate",
    "caption": "Table 3-2 Race and Ethnicity Distribution, 2000–2019",
    "extracted_text": "Table 3-2 Race and Ethnicity Distribution, 2000–2019 Race and Ethnicity Alameda Population 2000 2010 2019 White alone 56.9% 50.8% 48.2% Black or African American alone 6.2% 6.4% 7.4% American Indian or Alaska Native alone 0.7%",
    "page_image_path": ""
  },
  {
    "id": "lhmp_table_e7bfd5682d580b98",
    "city": "alameda",
    "source_document": "alameda-cahmp-2022.pdf",
    "pdf_page": 39,
    "page_label": "",
    "section_heading": "Asset Inventory | 3-4",
    "suggested_hazard": null,
    "extraction_reason": "PDF text matched a figure or table caption pattern.",
    "review_status": "candidate",
    "caption": "Table 3-3 Households by Income Level, 2017",
    "extracted_text": "Table 3-3 Households by Income Level, 2017 Income Level Renter Occupied Owner Occupied Total No. % No. % No. % Extremely Low Income ≤30% of AMI 3,440 11.2% 985",
    "page_image_path": ""
  },
  {
    "id": "lhmp_table_20cabb0d9712f9a8",
    "city": "alameda",
    "source_document": "alameda-cahmp-2022.pdf",
    "pdf_page": 41,
    "page_label": "",
    "section_heading": "",
    "suggested_hazard": "poor_air_quality",
    "extraction_reason": "Caption contained configured hazard alias “wildfire smoke”.",
    "review_status": "candidate",
    "caption": "Table 3-4 Historic and Projected Employment, 2010–2040",
    "extracted_text": "Table 3-4 Historic and Projected Employment, 2010–2040 Year Alameda Alameda County Total Employment % Change Total Employment % Change 2010 29,265 -- 705,540 -- 2020 38,905 32.9%",
    "page_image_path": ""
  },
  {
    "id": "lhmp_table_146cecab1266ab41",
    "city": "alameda",
    "source_document": "alameda-cahmp-2022.pdf",
    "pdf_page": 46,
    "page_label": "",
    "section_heading": "",
    "suggested_hazard": "flood",
    "extraction_reason": "Caption contained configured hazard alias “storm drain”.",
    "review_status": "candidate",
    "caption": "Table 3-5. City-Owned Sewer, Storm and Electrical Utilities",
    "extracted_text": "Table 3-5. City-Owned Sewer, Storm and Electrical Utilities Utility Amount Sewer Mains 142 miles Sewer Manholes 3,122 each Sewer Pump Stations 42 each Storm Pipes and Cross Culverts 90 miles Storm Manholes 2,058 each Storm Pump Stations 11 each Other Storm Structures (ex. Catchbasins, outlets)",
    "page_image_path": ""
  },
  {
    "id": "lhmp_table_854370e31f07be43",
    "city": "alameda",
    "source_document": "alameda-cahmp-2022.pdf",
    "pdf_page": 53,
    "page_label": "",
    "section_heading": "",
    "suggested_hazard": null,
    "extraction_reason": "PDF text matched a figure or table caption pattern.",
    "review_status": "candidate",
    "caption": "Table 3-6. Street Inventory",
    "extracted_text": "Table 3-6. Street Inventory Street Owned By Mileage City - Local Classification 113.2 City - Arterial Classification 33.5 Caltrans 4.9 Private & Federal 39.4 Total: 191.0 Bikeways 51.2 In addition to the City and State maintained streets, the following transportation structures are located",
    "page_image_path": ""
  },
  {
    "id": "lhmp_table_a23a3774290d8613",
    "city": "alameda",
    "source_document": "alameda-cahmp-2022.pdf",
    "pdf_page": 59,
    "page_label": "",
    "section_heading": "",
    "suggested_hazard": "sea_level_rise",
    "extraction_reason": "Caption contained configured hazard alias “sea level rise”.",
    "review_status": "candidate",
    "caption": "Table 4-1 Summary of Hazard Analysis",
    "extracted_text": "Table 4-1 Summary of Hazard Analysis Hazard Likelihood Consequence Hazards of Concern Earthquakes Likely Catastrophic Hazards of Greatest Concern Flooding from storms Likely Moderate to Catastrophic Sea level rise Likely Catastrophic",
    "page_image_path": ""
  },
  {
    "id": "lhmp_table_42d982cb558f4395",
    "city": "alameda",
    "source_document": "alameda-cahmp-2022.pdf",
    "pdf_page": 61,
    "page_label": "",
    "section_heading": "",
    "suggested_hazard": null,
    "extraction_reason": "PDF text matched a figure or table caption pattern.",
    "review_status": "candidate",
    "caption": "Table 4-2. MMI Intensity Table",
    "extracted_text": "Table 4-2. MMI Intensity Table Intensity Building Contents Masonry Buildings Multi-Family Wood- Frame Buildings 1&2 Story Wood- Frame Buildings MMI 6 Some things thrown from shelves, pictures shifted, water thrown from pools Some walls and parapets of poorly constructed buildings",
    "page_image_path": ""
  },
  {
    "id": "lhmp_table_f0237dd50f3fc0be",
    "city": "alameda",
    "source_document": "alameda-cahmp-2022.pdf",
    "pdf_page": 64,
    "page_label": "",
    "section_heading": "Historic Earthquakes",
    "suggested_hazard": "earthquake",
    "extraction_reason": "Caption contained configured hazard alias “fault rupture”.",
    "review_status": "candidate",
    "caption": "Table 4-3 and Table 4-4 show the historic recorded earthquakes along the Hayward and San Andreas",
    "extracted_text": "Table 4-3 and Table 4-4 show the historic recorded earthquakes along the Hayward and San Andreas Faults, respectively. Table 4-3. Recorded or Deduced Strong (M6.0+) Earthquakes along the Hayward Fault Date Magnitude Notes 1315 Over M6.3 Based on geologic data 1470 Over M6.3 Based on geologic data 1630 Over M6.3 Based on geologic data 1725",
    "page_image_path": ""
  },
  {
    "id": "lhmp_table_78b17c2b2ce71742",
    "city": "alameda",
    "source_document": "alameda-cahmp-2022.pdf",
    "pdf_page": 64,
    "page_label": "",
    "section_heading": "",
    "suggested_hazard": "earthquake",
    "extraction_reason": "Caption contained configured hazard alias “fault rupture”.",
    "review_status": "candidate",
    "caption": "Table 4-3. Recorded or Deduced Strong (M6.0+) Earthquakes along the Hayward Fault",
    "extracted_text": "Table 4-3. Recorded or Deduced Strong (M6.0+) Earthquakes along the Hayward Fault Date Magnitude Notes 1315 Over M6.3 Based on geologic data 1470 Over M6.3 Based on geologic data 1630 Over M6.3 Based on geologic data 1725 Over M6.3 Based on geologic data, predates California",
    "page_image_path": ""
  },
  {
    "id": "lhmp_table_513aee6c631efdd6",
    "city": "alameda",
    "source_document": "alameda-cahmp-2022.pdf",
    "pdf_page": 65,
    "page_label": "",
    "section_heading": "",
    "suggested_hazard": "earthquake",
    "extraction_reason": "Caption contained configured hazard alias “liquefaction”.",
    "review_status": "candidate",
    "caption": "Table 4-4. Recorded Strong (M6.0+) and Major (M7.0+) Earthquakes along the San Andreas Fault",
    "extracted_text": "Table 4-4. Recorded Strong (M6.0+) and Major (M7.0+) Earthquakes along the San Andreas Fault Date Magnitude Notes 1812 M7+ Southern California 1838 M7 Santa Cruz Mountains 1857 M7.9 Fort Tejon 1890 M6.3 Corralitos",
    "page_image_path": ""
  },
  {
    "id": "lhmp_table_87becaf955a89b68",
    "city": "alameda",
    "source_document": "alameda-cahmp-2022.pdf",
    "pdf_page": 78,
    "page_label": "",
    "section_heading": "",
    "suggested_hazard": "sea_level_rise",
    "extraction_reason": "Caption contained configured hazard alias “sea level rise”.",
    "review_status": "candidate",
    "caption": "Table 4-5 is taken from the CARP and presents the main TWL projections shown on Figures 4-12 and 4-",
    "extracted_text": "Table 4-5 is taken from the CARP and presents the main TWL projections shown on Figures 4-12 and 4- 13 (and referenced in the CARP) as well as additional projections, their respective elevations in NAVD88, the various flood scenarios represented by these TWLs, and the anticipated timing for these projections. Table 4-5 Total Water Levels, Flooding Scenarios, and Timing for Sea Level Rise Projections TWL Elevation (NAVD88) Flooding Scenarios: SLR + Storm Surge Timing for SLR Projections MHHW + 36” ~9.5 feet 50-year storm 6” SLR + 25-year storm 12” SLR + 5-year storm 18” SLR + 2-year storm",
    "page_image_path": ""
  },
  {
    "id": "lhmp_table_7c634a099191fa35",
    "city": "alameda",
    "source_document": "alameda-cahmp-2022.pdf",
    "pdf_page": 78,
    "page_label": "",
    "section_heading": "13 (and referenced in the CARP) as well as additional projections, their respective elevations in NAVD88,",
    "suggested_hazard": "sea_level_rise",
    "extraction_reason": "Caption contained configured hazard alias “sea level rise”.",
    "review_status": "candidate",
    "caption": "Table 4-5 Total Water Levels, Flooding Scenarios, and Timing for Sea Level Rise Projections",
    "extracted_text": "Table 4-5 Total Water Levels, Flooding Scenarios, and Timing for Sea Level Rise Projections TWL Elevation (NAVD88) Flooding Scenarios: SLR + Storm Surge Timing for SLR Projections MHHW + 36” ~9.5 feet 50-year storm 6” SLR + 25-year storm 12” SLR + 5-year storm 18” SLR + 2-year storm 24” SLR + king tide 36” SLR Immediate (storm risk)",
    "page_image_path": ""
  },
  {
    "id": "lhmp_table_8e4197833474548d",
    "city": "alameda",
    "source_document": "alameda-cahmp-2022.pdf",
    "pdf_page": 87,
    "page_label": "",
    "section_heading": "",
    "suggested_hazard": "earthquake",
    "extraction_reason": "Caption contained configured hazard alias “earthquake”.",
    "review_status": "candidate",
    "caption": "Table 4-6 Tsunamis in the San Francisco Bay with Measurements Recorded in Alameda",
    "extracted_text": "Table 4-6 Tsunamis in the San Francisco Bay with Measurements Recorded in Alameda Year Location Name Latitude Longitude Distance From Source (km) Travel Hours Maximum Water Height (m) 1946",
    "page_image_path": ""
  },
  {
    "id": "lhmp_table_2f737360c24845f0",
    "city": "alameda",
    "source_document": "alameda-cahmp-2022.pdf",
    "pdf_page": 95,
    "page_label": "",
    "section_heading": "",
    "suggested_hazard": "extreme_heat",
    "extraction_reason": "Caption contained configured hazard alias “extreme heat”.",
    "review_status": "candidate",
    "caption": "Table 4-7 Number of Extreme Heat Days and Warm Nights per Year in Alameda",
    "extracted_text": "Table 4-7 Number of Extreme Heat Days and Warm Nights per Year in Alameda Timeframe Number of Extreme Heat Days per Year when daily maximum temperature is above 89° F Number of Warm Nights per Year when daily minimum temperature is above 61.5° F Modeled Historical (1961-1990) 3 5 Mid-Century Projection (2035- 2064)* 6 25 End-Century Projection (2070-",
    "page_image_path": ""
  },
  {
    "id": "lhmp_table_5de8c8988d3d5bd6",
    "city": "alameda",
    "source_document": "alameda-cahmp-2022.pdf",
    "pdf_page": 100,
    "page_label": "",
    "section_heading": "Quality Monitoring District).",
    "suggested_hazard": "poor_air_quality",
    "extraction_reason": "Caption contained configured hazard alias “wildfire smoke”.",
    "review_status": "candidate",
    "caption": "Table 4-8 below lists the number of Spare the Air Days that were called by the Bay Area Air Quality",
    "extracted_text": "Table 4-8 below lists the number of Spare the Air Days that were called by the Bay Area Air Quality Management District because particulate matter (PM) was forecast to exceed national standards, as well as the number of days on which PM concentrations officially exceeded the state and federal health-based air quality standards. PM exceedance typically occurs because of winter time wood burning, but since 2020 has more commonly occurred in the summer as a result of wildfires. The Spare the Air Days shown in Table 4-8 were called for the entire 9-county Bay Area, including the City of Alameda.",
    "page_image_path": ""
  },
  {
    "id": "lhmp_table_513e3b3db019e6fb",
    "city": "alameda",
    "source_document": "alameda-cahmp-2022.pdf",
    "pdf_page": 101,
    "page_label": "",
    "section_heading": "",
    "suggested_hazard": "poor_air_quality",
    "extraction_reason": "Caption contained configured hazard alias “poor air quality”.",
    "review_status": "candidate",
    "caption": "Table 4-8 Number of Spare the Air Days Issued for Excess PM Levels",
    "extracted_text": "Table 4-8 Number of Spare the Air Days Issued for Excess PM Levels Year Spare the Air Alerts National 24 Hour PM 10 Excess Days CA 24 Hour PM Excess Days National 24 Hour PM 2.5 Excess Days 2022 0 0",
    "page_image_path": ""
  },
  {
    "id": "lhmp_table_4edf92635e5c51b0",
    "city": "alameda",
    "source_document": "alameda-cahmp-2022.pdf",
    "pdf_page": 114,
    "page_label": "",
    "section_heading": "",
    "suggested_hazard": null,
    "extraction_reason": "PDF text matched a figure or table caption pattern.",
    "review_status": "candidate",
    "caption": "Table 5-1 Adaptation Planning: Crown Beach",
    "extracted_text": "Table 5-1 Adaptation Planning: Crown Beach",
    "page_image_path": ""
  },
  {
    "id": "lhmp_table_1fce96b1f2e8eac3",
    "city": "alameda",
    "source_document": "alameda-cahmp-2022.pdf",
    "pdf_page": 115,
    "page_label": "",
    "section_heading": "",
    "suggested_hazard": null,
    "extraction_reason": "PDF text matched a figure or table caption pattern.",
    "review_status": "candidate",
    "caption": "Table 5-2 Adaptation Planning: Eastshore Drive",
    "extracted_text": "Table 5-2 Adaptation Planning: Eastshore Drive",
    "page_image_path": ""
  },
  {
    "id": "lhmp_table_c0044a7a51ccae37",
    "city": "alameda",
    "source_document": "alameda-cahmp-2022.pdf",
    "pdf_page": 116,
    "page_label": "",
    "section_heading": "",
    "suggested_hazard": null,
    "extraction_reason": "PDF text matched a figure or table caption pattern.",
    "review_status": "candidate",
    "caption": "Table 5-3 Adaptation Planning: Shoreline Near Webster and Posey Tubes",
    "extracted_text": "Table 5-3 Adaptation Planning: Shoreline Near Webster and Posey Tubes",
    "page_image_path": ""
  },
  {
    "id": "lhmp_table_a7bbbb46b2c3562d",
    "city": "alameda",
    "source_document": "alameda-cahmp-2022.pdf",
    "pdf_page": 117,
    "page_label": "",
    "section_heading": "",
    "suggested_hazard": null,
    "extraction_reason": "PDF text matched a figure or table caption pattern.",
    "review_status": "candidate",
    "caption": "Table 5-4 Adaptation Planning: Bay Farm Island Lagoon System 1 Outlet Gate and Seawall",
    "extracted_text": "Table 5-4 Adaptation Planning: Bay Farm Island Lagoon System 1 Outlet Gate and Seawall",
    "page_image_path": ""
  },
  {
    "id": "lhmp_table_7a64d0138e662205",
    "city": "alameda",
    "source_document": "alameda-cahmp-2022.pdf",
    "pdf_page": 118,
    "page_label": "",
    "section_heading": "",
    "suggested_hazard": null,
    "extraction_reason": "PDF text matched a figure or table caption pattern.",
    "review_status": "candidate",
    "caption": "Table 5-5 Adaptation Planning: Veteran’s Court Seawall",
    "extracted_text": "Table 5-5 Adaptation Planning: Veteran’s Court Seawall",
    "page_image_path": ""
  },
  {
    "id": "lhmp_table_49a11624978c704c",
    "city": "alameda",
    "source_document": "alameda-cahmp-2022.pdf",
    "pdf_page": 119,
    "page_label": "",
    "section_heading": "",
    "suggested_hazard": null,
    "extraction_reason": "PDF text matched a figure or table caption pattern.",
    "review_status": "candidate",
    "caption": "Table 5-6 Adaptation Planning: Bay Farm Island Touchdown and Towata Park",
    "extracted_text": "Table 5-6 Adaptation Planning: Bay Farm Island Touchdown and Towata Park",
    "page_image_path": ""
  },
  {
    "id": "lhmp_table_74f52527f3ceb42d",
    "city": "alameda",
    "source_document": "alameda-cahmp-2022.pdf",
    "pdf_page": 120,
    "page_label": "",
    "section_heading": "",
    "suggested_hazard": null,
    "extraction_reason": "PDF text matched a figure or table caption pattern.",
    "review_status": "candidate",
    "caption": "Table 5-7 Adaptation Planning: SR260, Including Posey and Webster Tubes",
    "extracted_text": "Table 5-7 Adaptation Planning: SR260, Including Posey and Webster Tubes",
    "page_image_path": ""
  },
  {
    "id": "lhmp_table_84b4fdbfaa6b2c46",
    "city": "alameda",
    "source_document": "alameda-cahmp-2022.pdf",
    "pdf_page": 121,
    "page_label": "",
    "section_heading": "",
    "suggested_hazard": null,
    "extraction_reason": "PDF text matched a figure or table caption pattern.",
    "review_status": "candidate",
    "caption": "Table 5-8 Adaptation Planning: SR61/Doolittle Drive",
    "extracted_text": "Table 5-8 Adaptation Planning: SR61/Doolittle Drive",
    "page_image_path": ""
  },
  {
    "id": "lhmp_table_eee5b1e9dfccdd6c",
    "city": "alameda",
    "source_document": "alameda-cahmp-2022.pdf",
    "pdf_page": 122,
    "page_label": "",
    "section_heading": "",
    "suggested_hazard": null,
    "extraction_reason": "PDF text matched a figure or table caption pattern.",
    "review_status": "candidate",
    "caption": "Table 5-9 Adaptation Planning: Critical and High-Use Roadways",
    "extracted_text": "Table 5-9 Adaptation Planning: Critical and High-Use Roadways",
    "page_image_path": ""
  },
  {
    "id": "lhmp_table_97a320cfe313f947",
    "city": "alameda",
    "source_document": "alameda-cahmp-2022.pdf",
    "pdf_page": 123,
    "page_label": "",
    "section_heading": "",
    "suggested_hazard": "flood",
    "extraction_reason": "Caption contained configured hazard alias “storm drain”.",
    "review_status": "candidate",
    "caption": "Table 5-10 Adaptation Planning: Storm Drain Pipes and Pump Stations",
    "extracted_text": "Table 5-10 Adaptation Planning: Storm Drain Pipes and Pump Stations",
    "page_image_path": ""
  },
  {
    "id": "lhmp_table_e3cc8fcff20c7fe6",
    "city": "alameda",
    "source_document": "alameda-cahmp-2022.pdf",
    "pdf_page": 124,
    "page_label": "",
    "section_heading": "",
    "suggested_hazard": null,
    "extraction_reason": "PDF text matched a figure or table caption pattern.",
    "review_status": "candidate",
    "caption": "Table 5-11 Adaptation Planning: Bayview Weir and Outfall",
    "extracted_text": "Table 5-11 Adaptation Planning: Bayview Weir and Outfall",
    "page_image_path": ""
  },
  {
    "id": "lhmp_table_48844e01aebb262a",
    "city": "alameda",
    "source_document": "alameda-cahmp-2022.pdf",
    "pdf_page": 127,
    "page_label": "",
    "section_heading": "",
    "suggested_hazard": "earthquake",
    "extraction_reason": "Caption contained configured hazard alias “earthquake”.",
    "review_status": "candidate",
    "caption": "Table 5-12 Key Partner Mitigation Strategies",
    "extracted_text": "Table 5-12 Key Partner Mitigation Strategies Owner/Manager Infrastructure Within City Known Hazard Mitigation Efforts East Bay Municipal Utility District (EBMUD)  Potable, non-potable (irrigation), and fire suppression water supply system consisting of pipelines, pumping plants, flow/pressure control facilities, and storage tanks and reservoirs",
    "page_image_path": ""
  },
  {
    "id": "lhmp_table_89f82c8486d426b0",
    "city": "alameda",
    "source_document": "alameda-cahmp-2022.pdf",
    "pdf_page": 132,
    "page_label": "",
    "section_heading": "Strategies",
    "suggested_hazard": "earthquake",
    "extraction_reason": "Caption contained configured hazard alias “ground shaking”.",
    "review_status": "candidate",
    "caption": "Table 5-13 Climate Adaptation and Hazard Mitigation Strategies",
    "extracted_text": "Table 5-13 Climate Adaptation and Hazard Mitigation Strategies Strategy Hazard(s) Addressed Lead Department Related Policy/ Plan Buildings B1. Solar Panels. Encourage installation of solar panels and energy storage equipment in existing and new development and on public property such as the former Doolittle Landfill. Earthquake Ground Shaking Wind/Storms",
    "page_image_path": ""
  },
  {
    "id": "lhmp_table_9c59a1218fc4035d",
    "city": "alameda",
    "source_document": "alameda-cahmp-2022.pdf",
    "pdf_page": 299,
    "page_label": "",
    "section_heading": "63 multi-family buildings containing approximately 1,000 units remain on the list of potentially hazardous",
    "suggested_hazard": "earthquake",
    "extraction_reason": "Caption contained configured hazard alias “earthquake”.",
    "review_status": "candidate",
    "caption": "Table E-1 Alameda's Soft-Story Building Inventory",
    "extracted_text": "Table E-1 Alameda's Soft-Story Building Inventory Description Number of Buildings Residential Units Designated Soft Story 209 ~4,500 Retrofitted 146 ~3,500 Not retrofitted 63 ~1,000 8 https://www.alamedaca.gov/Departments/Planning-Building-and-Transportation/Building/Seismic-Retrofit/Potential- Soft-Story-Buildings",
    "page_image_path": ""
  },
  {
    "id": "lhmp_table_9b0f309dd7ab0b59",
    "city": "alameda",
    "source_document": "alameda-cahmp-2022.pdf",
    "pdf_page": 311,
    "page_label": "",
    "section_heading": "",
    "suggested_hazard": "earthquake",
    "extraction_reason": "Caption contained configured hazard alias “liquefaction”.",
    "review_status": "candidate",
    "caption": "Table E-2 Seismic Status of Bridges and Tubes in Alameda",
    "extracted_text": "Table E-2 Seismic Status of Bridges and Tubes in Alameda Bridge/Tube Owner Year Built Seismic Performance Seismic Retrofit Notes High Street bridge Alameda County 1939 No collapse Retrofitted to “no collapse” standard in 2009. Park St bridge",
    "page_image_path": ""
  },
  {
    "id": "lhmp_table_f42c606096822ed2",
    "city": "alameda",
    "source_document": "alameda-cahmp-2022.pdf",
    "pdf_page": 315,
    "page_label": "",
    "section_heading": "",
    "suggested_hazard": "sea_level_rise",
    "extraction_reason": "Caption contained configured hazard alias “sea level rise”.",
    "review_status": "candidate",
    "caption": "Table F-1 People of Alameda Affected by Depth of Flooding",
    "extracted_text": "Table F-1 People of Alameda Affected by Depth of Flooding Population No. of People Affected at 100-yr Flood Event No. of People Affected at 39.5-in Sea Level Rise No. of People Affected at 100-yr Flood Event + 39.5- in Sea Level Rise Total Residents 10,241 15,394 28,015 Over Age 65",
    "page_image_path": ""
  },
  {
    "id": "lhmp_table_f6310ecd44288921",
    "city": "alameda",
    "source_document": "alameda-cahmp-2022.pdf",
    "pdf_page": 316,
    "page_label": "",
    "section_heading": "Alameda Economy",
    "suggested_hazard": "sea_level_rise",
    "extraction_reason": "Caption contained configured hazard alias “sea level rise”.",
    "review_status": "candidate",
    "caption": "Table F-2. Economy of Alameda Affected by Depth of Flooding",
    "extracted_text": "Table F-2. Economy of Alameda Affected by Depth of Flooding Types of Employees Affected No. of Employees Affected in 100- year Flood Event No. of Employees Affected at 39.5-in Sea Level Rise No. of Employees Affected at 100-yr Flood Event + 39.5- in Sea Level Rise Total Employees 2,394 5,961",
    "page_image_path": ""
  },
  {
    "id": "lhmp_table_acfd0ea665c7cfce",
    "city": "alameda",
    "source_document": "alameda-cahmp-2022.pdf",
    "pdf_page": 318,
    "page_label": "",
    "section_heading": "",
    "suggested_hazard": "sea_level_rise",
    "extraction_reason": "Caption contained configured hazard alias “sea level rise”.",
    "review_status": "candidate",
    "caption": "Table F-3 City-Owned Coastal Flood Vulnerable Buildings and Depths of Flooding",
    "extracted_text": "Table F-3 City-Owned Coastal Flood Vulnerable Buildings and Depths of Flooding City Building Approx. Ground Elevation at Building (NAVD88) Approx. Depth of Flooding at 100-yr Flood Event (Total Water Level = 10ft NAVD88) Approx. Depth of Flooding at 36-in Sea Level Rise (Total Water Level =",
    "page_image_path": ""
  },
  {
    "id": "lhmp_table_dde7f4b8c88ad1e8",
    "city": "alameda",
    "source_document": "alameda-cahmp-2022.pdf",
    "pdf_page": 319,
    "page_label": "",
    "section_heading": "",
    "suggested_hazard": "sea_level_rise",
    "extraction_reason": "Caption contained configured hazard alias “coastal flooding”.",
    "review_status": "candidate",
    "caption": "Table F-4. Privately-Owned Coastal Flood Vulnerable Buildings and Depths of Flooding",
    "extracted_text": "Table F-4. Privately-Owned Coastal Flood Vulnerable Buildings and Depths of Flooding Building Location within Given Flood Event Majority Building Type Approx. Range of Ground Elevations within Area (NAVD88) Approx. Depth of Flooding Range",
    "page_image_path": ""
  },
  {
    "id": "lhmp_table_34be333b8671c055",
    "city": "alameda",
    "source_document": "alameda-cahmp-2022.pdf",
    "pdf_page": 320,
    "page_label": "",
    "section_heading": "Land Use",
    "suggested_hazard": "sea_level_rise",
    "extraction_reason": "Caption contained configured hazard alias “sea level rise”.",
    "review_status": "candidate",
    "caption": "Table F-5 below shows the land uses most affected by the 100-year flood event or 36-inches of sea level",
    "extracted_text": "Table F-5 below shows the land uses most affected by the 100-year flood event or 36-inches of sea level rise.",
    "page_image_path": ""
  },
  {
    "id": "lhmp_table_571d3e06aff71eaa",
    "city": "alameda",
    "source_document": "alameda-cahmp-2022.pdf",
    "pdf_page": 321,
    "page_label": "",
    "section_heading": "",
    "suggested_hazard": "sea_level_rise",
    "extraction_reason": "Caption contained configured hazard alias “sea level rise”.",
    "review_status": "candidate",
    "caption": "Table F-5 Land Uses Most Affected by 100-Year Flood Event",
    "extracted_text": "Table F-5 Land Uses Most Affected by 100-Year Flood Event Area of Island Impacted by 100-Year Flood Event or 36-Inches of Sea Level Rise Land Uses Most Affected Main Island: Northern Shoreline #1: Business #2: Mixed-Use #3: Medium-Density Residential Eastern Shoreline Low-Density Residential Alameda Point #1: Mixed-Use #2: Wildlife Habitat",
    "page_image_path": ""
  },
  {
    "id": "lhmp_table_3a837c4552443727",
    "city": "alameda",
    "source_document": "alameda-cahmp-2022.pdf",
    "pdf_page": 322,
    "page_label": "",
    "section_heading": "",
    "suggested_hazard": "sea_level_rise",
    "extraction_reason": "Caption contained configured hazard alias “sea level rise”.",
    "review_status": "candidate",
    "caption": "Table F-6. Stormwater Pump Station Depths of Flooding",
    "extracted_text": "Table F-6. Stormwater Pump Station Depths of Flooding Stormwater Pump Station Approx. Ground Elevation at Station (NAVD88) Approx. Depth of Flooding at 100-year Flood Event (Total Water Level = 10ft NAVD88) Approx. Depth of Flooding at 36-in Sea Level Rise",
    "page_image_path": ""
  },
  {
    "id": "lhmp_table_9e4cd8b4da740eac",
    "city": "alameda",
    "source_document": "alameda-cahmp-2022.pdf",
    "pdf_page": 323,
    "page_label": "",
    "section_heading": "",
    "suggested_hazard": "sea_level_rise",
    "extraction_reason": "Caption contained configured hazard alias “sea level rise”.",
    "review_status": "candidate",
    "caption": "Table F-7. City-Owned Stormwater and Wastewater Utilities Affected by Flooding",
    "extracted_text": "Table F-7. City-Owned Stormwater and Wastewater Utilities Affected by Flooding Utility Quantity Approx. % Exposed to Current 100-year Flood, Total Water Level = 10ft NAVD88 Approx. % Exposed to 36-in Sea Level Rise, Total Water Level = ~ 9.5ft NAVD88 Stormwater Storm Pipes and Cross Culverts",
    "page_image_path": ""
  },
  {
    "id": "lhmp_table_be718c088d9d07ee",
    "city": "alameda",
    "source_document": "alameda-cahmp-2022.pdf",
    "pdf_page": 324,
    "page_label": "",
    "section_heading": "",
    "suggested_hazard": "sea_level_rise",
    "extraction_reason": "Caption contained configured hazard alias “sea level rise”.",
    "review_status": "candidate",
    "caption": "Table F-8. Electrical Utilities",
    "extracted_text": "Table F-8. Electrical Utilities Utility Amount % Exposed to Current 100-yr Flood % Exposed to 36-in Sea Level Rise Alameda Municipal Power Overhead Distribution 86 pole miles 10 5 Alameda Municipal Underground Distribution",
    "page_image_path": ""
  },
  {
    "id": "lhmp_table_2d0b3f8d0b5c8c44",
    "city": "alameda",
    "source_document": "alameda-cahmp-2022.pdf",
    "pdf_page": 325,
    "page_label": "",
    "section_heading": "",
    "suggested_hazard": "sea_level_rise",
    "extraction_reason": "Caption contained configured hazard alias “sea level rise”.",
    "review_status": "candidate",
    "caption": "Table F-9. Length of Major City Roadways within 100-year Flood Zone",
    "extracted_text": "Table F-9. Length of Major City Roadways within 100-year Flood Zone Major Roadways Impacted by Flooding (and Area of City) at 100-yr Flood Event Approx. Linear Footage (LF) Affected at Current 100-yr Flood Event (Total Water Level = 10ft NAVD88) Main Island: SR 260/Webster St. Leading to Posey Tube Portal Descent (Northern Shoreline) 3,000 LF SR 260/Webster St Loop Leading to Webster Tube Portal Descent",
    "page_image_path": ""
  },
  {
    "id": "lhmp_table_350b53844cf2eec7",
    "city": "alameda",
    "source_document": "alameda-cahmp-2022.pdf",
    "pdf_page": 326,
    "page_label": "",
    "section_heading": "",
    "suggested_hazard": "sea_level_rise",
    "extraction_reason": "Caption contained configured hazard alias “sea level rise”.",
    "review_status": "candidate",
    "caption": "Table F-10. City Roadways and Maximum Depth of Flooding at Their Low Points",
    "extracted_text": "Table F-10. City Roadways and Maximum Depth of Flooding at Their Low Points Major Roadways Impacted by Flooding (Area of City) at 100-yr Flood Event Approx. Lowest Ground Elevation within Flood Zone (NAVD88) Approx. Maximum Depth of Flooding at Current",
    "page_image_path": ""
  },
  {
    "id": "lhmp_table_7a004f6b50e5bd59",
    "city": "alameda",
    "source_document": "alameda-cahmp-2022.pdf",
    "pdf_page": 327,
    "page_label": "",
    "section_heading": "",
    "suggested_hazard": "sea_level_rise",
    "extraction_reason": "Caption contained configured hazard alias “sea level rise”.",
    "review_status": "candidate",
    "caption": "Table F-11. Shoreline Types, Perimeter Mileage, and Percentage of Each within Alameda",
    "extracted_text": "Table F-11. Shoreline Types, Perimeter Mileage, and Percentage of Each within Alameda Shoreline Type Perimeter Mileage Percentage of Overall Shoreline Protection Main Island: Rip Rap Revetment 10.27 51.3% Bulkhead 4.21 21.0% Residential Seawalls or Natural Shoreline Berm",
    "page_image_path": ""
  },
  {
    "id": "lhmp_table_d18174dc59b4196a",
    "city": "alameda",
    "source_document": "alameda-cahmp-2022.pdf",
    "pdf_page": 332,
    "page_label": "",
    "section_heading": "",
    "suggested_hazard": "sea_level_rise",
    "extraction_reason": "Caption contained configured hazard alias “coastal flooding”.",
    "review_status": "candidate",
    "caption": "Table F-12 Summary of Applicable Priority Coastal Flooding Locations",
    "extracted_text": "Table F-12 Summary of Applicable Priority Coastal Flooding Locations Shoreline Location Flood Zone and BFE (NAVD88) Type of Shoreline Approx. Top Elevation of Unaccredit ed Seawall at Location, if Present",
    "page_image_path": ""
  },
  {
    "id": "lhmp_table_f6181d57f5ec6cf3",
    "city": "alameda",
    "source_document": "alameda-cahmp-2022.pdf",
    "pdf_page": 339,
    "page_label": "",
    "section_heading": "Priority Coastal Inundation Locations | G-3",
    "suggested_hazard": "sea_level_rise",
    "extraction_reason": "Caption contained configured hazard alias “sea level rise”.",
    "review_status": "candidate",
    "caption": "Table G-1. Key Vulnerable Assets in Existing City Plans and Commitments",
    "extracted_text": "Table G-1. Key Vulnerable Assets in Existing City Plans and Commitments Asset Plan Alameda Point Shoreline (including Main Street Ferry Terminal) Alameda Point Master Infrastructure Plan (MIP) and Alameda Point Town Center and Waterfront Precise Plan City Hall West Alameda Point MIP Northern Waterfront Northern Waterfront Development Plans Shoreline Drive City's 2017–2019 Capital Budget Veteran's Court Seawall Storm Drain Master Plan 2008 (focus on capacity",
    "page_image_path": ""
  },
  {
    "id": "lhmp_table_e7ccc6696ac2ebed",
    "city": "alameda",
    "source_document": "alameda-cahmp-2022.pdf",
    "pdf_page": 340,
    "page_label": "",
    "section_heading": "",
    "suggested_hazard": "sea_level_rise",
    "extraction_reason": "Caption contained configured hazard alias “sea level rise”.",
    "review_status": "candidate",
    "caption": "Table G-2 shows the 11 location-based priority flooding assets identified during the vulnerability",
    "extracted_text": "Table G-2 shows the 11 location-based priority flooding assets identified during the vulnerability assessment, two of which include various locations. Figure G-1 shows their locations spatially on Alameda Island, while Figure G-2 shows the flooding areas on Bay Farm Island.",
    "page_image_path": ""
  },
  {
    "id": "lhmp_table_f642a7936638434e",
    "city": "alameda",
    "source_document": "alameda-cahmp-2022.pdf",
    "pdf_page": 341,
    "page_label": "",
    "section_heading": "Priority Coastal Inundation Locations | G-5",
    "suggested_hazard": "sea_level_rise",
    "extraction_reason": "Caption contained configured hazard alias “sea level rise”.",
    "review_status": "candidate",
    "caption": "Table G-2. Location-Based Priority Flooding Assets",
    "extracted_text": "Table G-2. Location-Based Priority Flooding Assets Asset Category Asset Name ID for Figures 4-8 and 4-9 Exposure (Sea Level Rise)a Exposure (25-Year Flood)b Sensitivityc Consequenced Adaptive Capacitye Shoreline, Natural, and",
    "page_image_path": ""
  },
  {
    "id": "lhmp_table_be53a43b9bcbfb18",
    "city": "alameda",
    "source_document": "alameda-cahmp-2022.pdf",
    "pdf_page": 344,
    "page_label": "",
    "section_heading": "Priority Coastal Inundation Locations | G-8",
    "suggested_hazard": "sea_level_rise",
    "extraction_reason": "Caption contained configured hazard alias “sea level rise”.",
    "review_status": "candidate",
    "caption": "Table G-3. Crown Memorial State Beach Vulnerability Summary",
    "extracted_text": "Table G-3. Crown Memorial State Beach Vulnerability Summary Crown Memorial State Beach is a popular spot for recreation and education in Alameda. It has a pickleweed salt marsh that provides bird habitat in the Elsie Roemer Bird Sanctuary at the east end of the beach, as well as an eelgrass bed just offshore of the beach that provides juvenile fish habitat. Crown Beach and the bird sanctuary make up the majority of the natural shoreline on Alameda Island and are at substantial risk of erosion due to wave action and inundation from sea level rise. Key Issue(s)  The narrow beach is vulnerable to sea level rise and storm surge flooding, as well as erosion due to wave action. It is backed by a road, housing, and shopping centers, giving it little capacity to migrate inland. Decisions on adaptation will involve the City (owns the land), East Bay Regional Parks District (EBRPD; manages the beach), and the community at large. Exposure  Lower elevation portions of the sandy beach are currently susceptible to flooding at king tides. Large portions of the beach and bird sanctuary are inundated at 36” total water level, at which point small segments of Shoreline Drive also experience flooding originating at this location. At 48” total water level, nearly all of the beach and bird sanctuary are overtopped, leading to flooding of adjacent neighborhoods. Sensitivity Governance",
    "page_image_path": ""
  },
  {
    "id": "lhmp_table_50ec423c6244d852",
    "city": "alameda",
    "source_document": "alameda-cahmp-2022.pdf",
    "pdf_page": 346,
    "page_label": "",
    "section_heading": "Priority Coastal Inundation Locations | G-10",
    "suggested_hazard": "sea_level_rise",
    "extraction_reason": "Caption contained configured hazard alias “sea level rise”.",
    "review_status": "candidate",
    "caption": "Table G-4. Eastshore Drive (Adjacent Shoreline) Vulnerability Summary",
    "extracted_text": "Table G-4. Eastshore Drive (Adjacent Shoreline) Vulnerability Summary Eastshore Drive is the easternmost, north-south-oriented road on Alameda Island, providing access to the Eastshore and Fernside neighborhoods. These residential neighborhoods have many homes with private docks in San Leandro Bay. Although there are several designated points of public access along Eastshore Drive, there are no extensive public trails or parks along the shoreline. Private homes dominate the eastern waterfront. The Federal Emergency Management Agency (FEMA) recently determined that sections of the Eastshore neighborhood are within the 1 percent annual chance floodplain. Key Issue(s)  The Eastshore area is a low-lying section of the city with a large residential area vulnerable to flooding from sea level rise and storm events. There is limited space for adaptation because homes are built out very close to the waterfront. A potentially complex collaboration with homeowners and related groups (e.g., homeowners’ associations [HOAs]) will be necessary to agree upon shoreline protection measures due to ownership in this area. Exposure  Overtopping of existing shoreline structures in this area begins at 36” total water level, at which point floodwaters extend inland, inundating portions of Fernside Boulevard, the stormwater pump station serving this area, and areas as far inland as the fields near the Harrison Recreation Center. Initial shoreline overtopping is likely restricted to small sections of the shoreline (e.g., at the end of Liberty Drive), but more",
    "page_image_path": ""
  },
  {
    "id": "lhmp_table_fd9097c971787e9c",
    "city": "alameda",
    "source_document": "alameda-cahmp-2022.pdf",
    "pdf_page": 348,
    "page_label": "",
    "section_heading": "Priority Coastal Inundation Locations | G-12",
    "suggested_hazard": "sea_level_rise",
    "extraction_reason": "Caption contained configured hazard alias “sea level rise”.",
    "review_status": "candidate",
    "caption": "Table G-5. Shoreline Adjacent to Webster and Posey Tubes Vulnerability Summary",
    "extracted_text": "Table G-5. Shoreline Adjacent to Webster and Posey Tubes Vulnerability Summary The area of concern is the shoreline immediately adjacent to the Webster and Posey Tubes along the northern shore of Alameda Island. Numerous development projects are in the planning stage along the northern waterfront, and any long-term strategy to address flooding along the northern waterfront requires a coordinated approach across all new development projects and areas between. The shoreline in this area is lined with marinas, yacht brokerages, houseboats, and some shoreline public trails, and it is composed of a combination of levees and seawalls. Key Issue(s)  Overtopping of the shoreline near the tubes leads to inundation of one of the most critical transportation corridors in Alameda, including Webster Street and the tubes themselves. The proximity of businesses along the northern shoreline will pose design challenges for shoreline modifications, which must maintain public access to the waterfront. Numerous sensitive assets in this area would be inundated if the shoreline overtops; many assets were recently added to the FEMA 1 percent annual chance floodplain. Exposure  Shoreline overtopping begins at 36” total water level, at which point several buildings—such as the Oakmont of Mariner Point and Mariner Square Shopping Center—are at risk of inundation, as well as key assets like the Webster and Posey portals. Webster Street initial overtopping is restricted to a small (< 1,000-foot) section of shoreline in the immediate area, but more substantial shoreline overtopping occurs at higher water levels. Sensitivity",
    "page_image_path": ""
  },
  {
    "id": "lhmp_table_37ff17f6a78b5222",
    "city": "alameda",
    "source_document": "alameda-cahmp-2022.pdf",
    "pdf_page": 350,
    "page_label": "",
    "section_heading": "Priority Coastal Inundation Locations | G-14",
    "suggested_hazard": "flood",
    "extraction_reason": "Caption contained configured hazard alias “flooding”.",
    "review_status": "candidate",
    "caption": "Table G-6. Bay Farm Island Bridge Touchdown and Towata Park Vulnerability Summary",
    "extracted_text": "Table G-6. Bay Farm Island Bridge Touchdown and Towata Park Vulnerability Summary The stretch of shoreline near the Bay Farm Island Bridge touchdown on Alameda Island provides flood protection to the adjacent residential area, Bridgeview Isle, and Krusi Park. Overtopping at this location begins at 24” total water level but does not impact residential areas until 36” total water level. The current shoreline is composed of seawalls and riprap with a mix of City and Raven’s Cove HOA ownership. The City owns and maintains Towata Park at this location, which is impacted by flooding at 36” total water level. Key Issue(s)  Shoreline protection structures in this area currently provide flood protection for surrounding roads, residential neighborhoods, and Krusi and Towata Parks. Floodwater originating in this area may merge with water derived from overtopping in other areas at higher water levels, leading to substantial inundation that is only addressed with shoreline modifications in several locations. Exposure  Minor overtopping of the shoreline directly west of the bridge touchdown on Alameda Island begins at 24” total water level. At 36” total water level, Bridgeview Isle and some nearby houses are impacted. At 48” total water level and higher, the flood area expands significantly with several important streets and other assets impacted. Flooding at higher water levels could connect with the lagoons, leading to more widespread inundation. Sensitivity",
    "page_image_path": ""
  },
  {
    "id": "lhmp_table_6eb04e3e7df271b7",
    "city": "alameda",
    "source_document": "alameda-cahmp-2022.pdf",
    "pdf_page": 352,
    "page_label": "",
    "section_heading": "Priority Coastal Inundation Locations | G-16",
    "suggested_hazard": "sea_level_rise",
    "extraction_reason": "Caption contained configured hazard alias “sea level rise”.",
    "review_status": "candidate",
    "caption": "Table G-7. Bay Farm Island Lagoon System 1 North Outlet Gate and Seawall Vulnerability Summary",
    "extracted_text": "Table G-7. Bay Farm Island Lagoon System 1 North Outlet Gate and Seawall Vulnerability Summary The Bay Farm Island lagoon system draws water at the southern end and discharges it at the North Outlet Gate, located just west of Bay Farm Island Bridge. The shoreline at the outlet gate is a narrow isthmus of land that provides flood protection but is not a certified seawall or levee. The outlet gate is used to manage water levels in the lagoon through a passive tide gate system (currently inoperable) and an active pump. The shoreline in this area is a critical point of protection for the lagoon system and the homes that surround it. Key Issue(s)  The lagoon system is at risk of flooding due to issues at the outlet gate, including a slow pump that cannot rapidly lower water levels, an inoperable tide gate, and deficiencies in the seawall at that location. Overtopping of the shoreline in this area could inundate the lagoon system and lead to substantial flooding in surrounding neighborhoods. Exposure  Overtopping at the outlet gate seawall is likely at 36” total water level, potentially leading to overtopping of the banks of the lagoon and flooding of adjacent neighborhoods. Beyond 36” total water level, floodwaters originating at this location merge with floodwaters from elsewhere on Bay Farm Island, leading to substantial inundation across the island. Sensitivity Governance",
    "page_image_path": ""
  },
  {
    "id": "lhmp_table_8a7133aea04bdd5d",
    "city": "alameda",
    "source_document": "alameda-cahmp-2022.pdf",
    "pdf_page": 354,
    "page_label": "",
    "section_heading": "Priority Coastal Inundation Locations | G-18",
    "suggested_hazard": "sea_level_rise",
    "extraction_reason": "Caption contained configured hazard alias “sea level rise”.",
    "review_status": "candidate",
    "caption": "Table G-8. Veteran’s Court Seawall Vulnerability Summary",
    "extracted_text": "Table G-8. Veteran’s Court Seawall Vulnerability Summary Veteran’s Court is a small road near the Bay Farm Island Bridge touchdown on Bay Farm Island. It connects to Island Drive and serves primarily as an access road to the shore for maintenance or recreation. Veteran’s Memorial Park is also considered part of this priority shoreline area due to its importance to flood mitigation strategies. Veteran’s Court itself serves as a conduit for floodwaters if the seawall in this area is breached, potentially contributing to substantial inundation along Island Drive and adjacent neighborhoods. Key Issue(s)  The Veteran’s Court area is located within the FEMA 1 percent annual chance floodplain. Overtopping of this shoreline results in flooding at a major intersection on Bay Farm Island (Doolittle and Island Drives). While there are options for adapting this specific section of low-elevation shoreline, other shoreline areas across Bay Farm Island also overtop at similar water levels. Beyond 36” total water level, a coordinated response to shoreline overtopping on Bay Farm Island is needed to prevent flooding. Exposure  The Veteran’s Court seawall overtops at 36” total water level, below the FEMA base flood elevation (10’ NAVD88). At 48” total water level, inundation from Veteran’s Court merges with inundation from other overtopped shorelines on Bay Farm Island, making it difficult to determine the exact source of floodwaters. The Veteran’s Court area is likely responsible for some component of flooding at the intersection of Island Drive and Doolittle Drive.",
    "page_image_path": ""
  },
  {
    "id": "lhmp_table_4d967b782f1b676e",
    "city": "alameda",
    "source_document": "alameda-cahmp-2022.pdf",
    "pdf_page": 356,
    "page_label": "",
    "section_heading": "Priority Coastal Inundation Locations | G-20",
    "suggested_hazard": "flood",
    "extraction_reason": "Caption contained configured hazard alias “flooding”.",
    "review_status": "candidate",
    "caption": "Table G-9. Bay Farm Island Bridge Touchdown and Towata Park Vulnerability Summary",
    "extracted_text": "Table G-9. Bay Farm Island Bridge Touchdown and Towata Park Vulnerability Summary The stretch of shoreline near the Bay Farm Island Bridge touchdown on Alameda Island provides flood protection to the adjacent residential area, Bridgeview Isle, and Krusi Park. Overtopping at this location begins at 24” total water level but does not impact residential areas until a total water level of 36”. The current shoreline is composed of seawalls and riprap with a mix of City and Raven’s Cove HOA ownership. Towata Park at this location is owned and maintained by the City and is impacted by flooding by 36” total water level. Key Issue(s)  Shoreline protection structures in this area currently provide flood protection for surrounding roads, residential neighborhoods, and Krusi and Towata Parks. Floodwater originating in this area may merge with water derived from overtopping in other areas at higher water levels, leading to substantial inundation that is only addressed with shoreline modifications in several locations. Exposure  Minor overtopping of the shoreline directly west of the bridge touchdown on Alameda Island begins at 24” total water level. At 36” total water level, Bridgeview Isle and some nearby houses are impacted. At 48” total water level and higher, the flood area expands significantly with several important streets and other assets impacted. Flooding at higher water levels could connect with the lagoons, leading to more widespread inundation. Sensitivity Governance",
    "page_image_path": ""
  },
  {
    "id": "lhmp_table_c5dd6e0c3682b485",
    "city": "alameda",
    "source_document": "alameda-cahmp-2022.pdf",
    "pdf_page": 358,
    "page_label": "",
    "section_heading": "Priority Coastal Inundation Locations | G-22",
    "suggested_hazard": "sea_level_rise",
    "extraction_reason": "Caption contained configured hazard alias “sea level rise”.",
    "review_status": "candidate",
    "caption": "Table G-10. SR260, Including Webster and Posey Tubes, Vulnerability Summary",
    "extracted_text": "Table G-10. SR260, Including Webster and Posey Tubes, Vulnerability Summary SR260 is a critical transportation corridor connecting Alameda and Oakland—the tubes are one of four ways on or off Alameda Island. The historic average annual daily traffic at the tubes is approximately 31,500, including numerous commercial vehicles, which account for approximately 2.5 percent of daily traffic. The Posey Tube is the second oldest underwater tunnel in the United States (built in 1928) and was added to the National Register of Historic Places in 2000. Although seismic retrofits were completed in 2004, the age of the tube may increase its vulnerability to climate impacts. Webster Tube, built in 1963 to ease traffic volume in Posey Tube, is at lower risk of age-related deterioration. Key Issue(s)  SR260 is essential to the movement of people, goods, and emergency services. However, the tubes are vulnerable to flooding derived from both shoreline overtopping and precipitation events. Mixed jurisdictional oversight of the asset(s) could also pose a barrier to the implementation of adaptation measures, primarily because Caltrans is not specifically authorized to implement resilience/adaptation projects (but can incorporate adaptation/resilience into larger transportation projects). Exposure  SR260 and the tubes are exposed to sea level rise and storm surge flooding at 36” total water level. Inundation likely originates along the northern shoreline adjacent to the tubes (as described in the summary for that shoreline area). Overtopping near the Main Street Ferry Terminal may also contribute to flooding at the tubes. There is also substantial exposure to storm drain flooding driven by precipitation events",
    "page_image_path": ""
  },
  {
    "id": "lhmp_table_e161f8bf80782ac5",
    "city": "alameda",
    "source_document": "alameda-cahmp-2022.pdf",
    "pdf_page": 359,
    "page_label": "",
    "section_heading": "Priority Coastal Inundation Locations | G-23",
    "suggested_hazard": "sea_level_rise",
    "extraction_reason": "Caption contained configured hazard alias “sea level rise”.",
    "review_status": "candidate",
    "caption": "Table G-11. SR61 (Doolittle Drive and Other Segments) Vulnerability Summary",
    "extracted_text": "Table G-11. SR61 (Doolittle Drive and Other Segments) Vulnerability Summary SR61 is a state highway owned and maintained by Caltrans. The route runs from the intersection with SR112 near Oakland Airport and terminates on Alameda Island at the intersection of Webster Street and Central Avenue. The road connects Bay Farm Island and Alameda Island across the Bay Farm Island Bridge. Multiple AC Transit bus routes use SR61, including several that serve transit-dependent or disadvantaged communities. The City of Alameda has designated SR61 south of Otis Drive as a primary evacuation route and the segment on Alameda Island as critical access for the evacuation route. Key Issue(s)  Disruptions to SR61 could have substantial impacts on the flow of commuters and goods within Alameda and to Oakland, including several important bus routes. Existing traffic issues in Alameda would be exacerbated if the City closes SR61 or restricts traffic flow. Overtopping of Doolittle Drive on Bay Farm Island also contributes to broad flooding across the island, with the road serving as a conduit for floodwaters. Exposure  SR61 is exposed to flooding from multiple sources of overtopping, including Veteran’s Court seawall, along Doolittle Drive, and at the Bay Farm Island Bridge touchdown on Alameda Island. Shoreline overtopping begins at around 36” total water level. Precipitation-driven storm drain flooding also impacts SR61—the modeled 25-year storm event results in several areas with water levels greater than 0.5 feet above street level.",
    "page_image_path": ""
  },
  {
    "id": "lhmp_table_b441bd9c04c91765",
    "city": "alameda",
    "source_document": "alameda-cahmp-2022.pdf",
    "pdf_page": 360,
    "page_label": "",
    "section_heading": "Priority Coastal Inundation Locations | G-24",
    "suggested_hazard": "sea_level_rise",
    "extraction_reason": "Caption contained configured hazard alias “sea level rise”.",
    "review_status": "candidate",
    "caption": "Table G-12. Critical and High-Use Roadways (Excluding Caltrans Roads) Vulnerability Summary",
    "extracted_text": "Table G-12. Critical and High-Use Roadways (Excluding Caltrans Roads) Vulnerability Summary Many major and minor roads in Alameda are expected to be impacted by flooding and inundation associated with both sea level rise and storm events. To analyze and present vulnerabilities, key roadways were bundled into a single priority asset group. The common theme for roadways in this asset group is that they are heavily used by multiple AC Transit bus routes, specifically those that serve transit-dependent or socially vulnerable communities and provide critical connections between Alameda and the mainland. Although roadways other than those described here are at risk of damage due to flooding, this assessment prioritized roads that serve as key transit corridors because of their importance to transit-dependent communities. Key Issue(s)  Entire roads and specific road segments or intersections in Alameda are exposed to flooding from sea level rise, storm surge, and major rainfall events. Given the limited number of connections between Alameda and the mainland, disruptions to key roads like Webster Street can have large impacts on transit-dependent residents and commerce. One key vulnerability is the inability of connecting streets in Alameda to handle additional traffic volume if key roads are closed or restricted and major traffic rerouting is necessary. Exposure  Most of the exposure to key roadway segments is due to precipitation-driven, storm drain flooding—some segments are exposed to sea level rise and storm surge flooding in isolated locations. There is substantial exposure to storm drain flooding as modeled for a 25-year storm event.",
    "page_image_path": ""
  },
  {
    "id": "lhmp_table_f2a31514237dcbcd",
    "city": "alameda",
    "source_document": "alameda-cahmp-2022.pdf",
    "pdf_page": 363,
    "page_label": "",
    "section_heading": "Priority Coastal Inundation Locations | G-27",
    "suggested_hazard": "sea_level_rise",
    "extraction_reason": "Caption contained configured hazard alias “sea level rise”.",
    "review_status": "candidate",
    "caption": "Table G-13. Storm Drain Pipes and Pump Stations Vulnerability Summary",
    "extracted_text": "Table G-13. Storm Drain Pipes and Pump Stations Vulnerability Summary Storm drain pump stations across Alameda are a critical component of the stormwater system and are expected to become even more important as water levels rise. The pump stations operate in areas that cannot drain through a gravity system, although it is likely that most of the gravity-fed components of Alameda’s stormwater system will become obsolete as outfalls are submerged and rising groundwater impacts hydraulic conditions. Key Issue(s)  Alameda’s storm drain pump stations are already subject to capacity and operational issues, including flap gate failures, sedimentation, and lack of backup power. While capacity upgrades have already been identified, the City must consider other modifications at the pump stations to increase the resilience of the station infrastructure to floodwater. Exposure  Shoreline overtopping due to sea level rise and storm surge at multiple locations could lead to temporary flooding or permanent inundation at storm drain pump stations. Precipitation-driven storm drain flooding could also impact the pump stations. The degree of flooding varies from",
    "page_image_path": ""
  },
  {
    "id": "lhmp_table_8bd8b1d4deac7d30",
    "city": "alameda",
    "source_document": "alameda-cahmp-2022.pdf",
    "pdf_page": 364,
    "page_label": "",
    "section_heading": "Priority Coastal Inundation Locations | G-28",
    "suggested_hazard": "sea_level_rise",
    "extraction_reason": "Caption contained configured hazard alias “sea level rise”.",
    "review_status": "candidate",
    "caption": "Table G-14. Bayview Weir and Outfall Vulnerability Summary",
    "extracted_text": "Table G-14. Bayview Weir and Outfall Vulnerability Summary Water levels in the South Shore Lagoons are maintained by the Bayview weir and outfall, located near the Elsie Roemer Bird Sanctuary. Water is pumped into the lagoon system at the west end at high tide and released from the Bayview outfall at low tide to move water through the lagoon system at a rate that prevents stagnation and water quality issues. The Bayview weir functions as a barrier between lagoon waters and the Bay. The location of the weir and outfall is shown on the map for Crown Beach and the bird sanctuary earlier in this appendix. Key Issue(s)  The Bayview weir and outfall system is an important component of the South Shore Lagoons. An operational lagoon system is important to maintain water quality and to prevent flooding in communities adjacent to the lagoons. The current weir and outfall are at high risk of sea level rise and storm surge, and they need major repairs and/or replacement. The greatest vulnerability to the weir and outfall system is from sea level rise, which will eventually prevent the gravity-fed system from operating, necessitating an active pump. Exposure",
    "page_image_path": ""
  }
]
